{"FECHA":"2025-01-31","NUMERO":"3452/2025","TITULO":"3452/2025 - Declara de Interés 25 Años de CLAAS Argentina en Sunchales.","TEXTO":"<p><u>DECRETO N° 3452/2025<br>VISTO:<br></u>El 25° Aniversario de CLAAS Argentina en Sunchales; y,<br><u>CONSIDERANDO:<br></u>Que CLAAS Argentina nació el 15 de enero de 2000 en nuestra ciudad de Sunchales, instalándose así en el país una subsidiaria de la empresa familiar alemana, líder en su rubro en todo el mundo.-<br>Que desde entonces ha pasado de tener 4 a 10 sucursales en todo el territorio argentino, abasteciendo además a países limítrofes, tendiendo una red que incluye a más de 3.894 persona, entre las que se encuentran 170 empleados, 24 agentes de ventas, 1.300 proveedores y 2.400 clientes.-<br>Que CLAAS Argentina a contribuidoal desarrollo agrícola de nuestra región y del sector agroindustrial en su conjunto, siendo reconocida por su innovación y copromiso con el desarrollo sostenible de la producción agropecuaria.-<br>Que en su 25° Aniversario, la marca consolida su rol como proveedora de la más evolucionada tecnología en forrajes y cosecha en el mercado local y afianza el vínculo con sus clientes y aliados estratégicos.-<br>Que es meritorio reconocer la proyección y compromiso de CLAAS Argentina en nuestro territorio.-<br>Por todo ello, El Intendente Municipal de la ciudad de Sunchales, en uso de las facultades que le confiere la Ley Orgánica de Municiaplidades N° 2.756:<br><u>DECRETA:<br></u>Artículo 1°: Declárese de Interés Municipal el 25° Aniversario de CLAAS Argentina en Sunchales.<br>Artículo 2°: Entréguese copia del presente al Presidente de CLAAS Argentina.<br>Artículo 3°: Refréndese el presente por la Sra. Secretaria de Gobierno.<br>Artículo 4°: Regístrese, comuníquese, notifíquese, publíquese y archívese.<br></p>","NOMBRE_PDF":"217-digesto.pdf","OBSERVACION":null,"NOMBRE_TIPO":"Decreto","ID_DIGESTO":217}