{"FECHA":"2023-06-05","NUMERO":"3259/2023","TITULO":"3259/2023 - Designa a la Sra. Lilia Yacomosky en el cargo de Directora de Proyectos, a partir del 05/06/2023.","TEXTO":"<p><u>DECRETO N° 3259/2023<br>VISTO:<br></u>La Ordenanza N° 3071/2023 que establece el Organigrama Municipal y;<u><br>CONSIDERANDO:<br></u>Que resulta necesario proceder a las designaciones de aquellos funcionarios que ocuparan los cargos que se encuentran vacantes.-<br>Que en virtud del Art. 41° de la Ley N° 2756, el Intendente tiene la atribución de designar a sus colaboradores directos, quienes Io acompañaran en su accionar de gobierno.-<br>Por ello, El Intendente Municipal de la ciudad de Sunchales, en uso de las facultades que le son propias,<u><br>DECRETA:<br></u>Articulo 1°: Designase a la Sra. Lilia Yacomosky, D.N.I. N° 25.379.846, en el cargo de Directora de Proyectos, a partir del 05 de junio de 2.023.-<br>Articulo 2°: El presente sera refrendado por el Secretario de Gestión. <br>Articulo 3°: Remitase copia del presente Decreto a la Sra. Lilia Yacomosky.<br>Articulo 4°: Registrese, publiquese, comuniquese y archivese.-</p>","NOMBRE_PDF":"524-digesto.pdf","OBSERVACION":null,"NOMBRE_TIPO":"Decreto","ID_DIGESTO":524}