{"FECHA":"2023-03-16","NUMERO":"3091/2023","TITULO":"3091/2023 - Establece que calle Actis, desde calle Güemes hasta calle Gabasio tendrá un sentido único de circulación de Sur a Norte.","TEXTO":"<p><u>ORDENANZA N° 3091/2023<br></u>ARTÍCULO 1º.- Establécese que calle Actis, desde calle Güemes hasta calle Gabasio tendrá un sentido único de circulación de Sur a Norte.-<br>ARTÍCULO 2º.- Dese al Departamento Ejecutivo Municipal para su promulgación, comuníquese, publíquese, archívese y dese al R. de R. D. y O.-</p>","NOMBRE_PDF":"593-digesto.pdf","OBSERVACION":null,"NOMBRE_TIPO":"Ordenanza","ID_DIGESTO":593}