{"FECHA":"2023-02-23","NUMERO":"3230/2023","TITULO":"3230/2023 - Aprueba lo actuado por la Junta Examinadora de la convocatoria a prueba de selección de personal para GUS como agentes de Guardia Vial, bajo la modalidad de personal contratado no permanente y establece el Orden de Mérito  Definitivo del Concurso.","TEXTO":"<p><u>DECRETO N° 3230/2023<br>VISTO:</u> El Decreto N° 3291/2022 y;<u><br>CONSIDERANDO:<br></u>Que la mencionada norma dispone la convocatoria a prueba de selecciónn de personal para Gus como agentes de Guardia Vial, bajo la modalidad de personal contratado no permanente, conforme los términos y condiciones de previstas en los Anexos I, II,II y IV.-.<br>Que habiendo culminado el tramite del Concurso se elevan las Actas emitidas por la Junta Examinadora actuante y Planilla de Orden de Merito Final.-<br>Que corresponde dictar el acto administrativo pertinente, cuyo objeto disponga aprobar el Orden de Mérito Definitivo que como Anexo se adjunta.-<br>Por ello, El Intendente Municipal de la ciudad de Sunchales, en uso de las facultades que le son propias, <u><br>DECRETA:<br></u>Articulo 1°: Apruebese Io actuado por la Junta Examinadora de la convocatoria a prueba de selección de personal para Gus como agentes de Guardia Vial, bajo la modalidad de personal contratado no permanente; dispuesto por Decreto N°3291/22.-<br>Articulo 2°: Establecese el Orden de Mérito Definitivo del Concurso mencionado, que como Anexo integra el presente Decreto.<br>Articulo 3°: Refrendese el presente Decreto por el señor Secretario de Gestión.- <br>Articulo 4°: Regístrese, comuníquese, publíquese y archívese.-<br></p>","NOMBRE_PDF":"678-digesto.pdf","OBSERVACION":null,"NOMBRE_TIPO":"Decreto","ID_DIGESTO":678}