{"FECHA":"2022-03-09","NUMERO":"3102/2022","TITULO":"3102/2022 - Aprobación de Acta Acuerdo sobre condiciones de los empleados asignados a la Guardia Urbana Sunchalense (GUS), suscrita con el Sindicato de Obreros y Empleados Municipales (SOEM) el 17 de febrero de 2022.","TEXTO":"<p><u>DECRETO N° 3102/2022<br>VISTO:</u> El Acta Acuerdo suscripto con el Sindicato de Obreros y Empleados Municipales (SOEM) en fecha 17 de febrero de 2022 y;<u><br>CONSIDERACIÓN:<br></u>Que por la citada Acta se acuerda con el Sindicato de Obreros y Empleados Municipales (SOEM) sobre distintos aspectos que tienen como objetivo la situación de los trabajadores asignados a la Guardia Urbana Sunchalense.<br>Que, en particular, se desarrollan temáticas que refieren a la remuneración de los trabajadores y a sus condiciones de salud laboral.<br>Por ello, El Intendente Municipal de la ciudad de Sunchales, en uso de las facultades que le son propias,<u><br>DECRETA:<br></u>Artículo 1°: Apruébese el Acta Acuerdo sobre condiciones de los empleados asignados a la Guardia Urbana Sunchalense (GUS), suscripta con el Sindicato de Obreros y Empleados Municipales (SOEM) el día 17 de febrero de 2022 que como Anexo forma parte integrante de la presente Resolución.-<br>Artículo 2°: Remítase copia del presente al Sindicato de Obreros y Empleados Municipales (SOEM) y a la Subdirección de Personal.-<br>Artículo 3°: Regístrese, publíquese, comuníquese y archívese.-</p>","NOMBRE_PDF":"999-digesto.pdf","OBSERVACION":null,"NOMBRE_TIPO":"Decreto","ID_DIGESTO":999}